seas/__init__.py
seas/colormaps.py
seas/config.txt
seas/defaults.py
seas/domains.py
seas/experiment.py
seas/filemanager.py
seas/gui.py
seas/hdf5manager.py
seas/ica.py
seas/rois.py
seas/signalanalysis.py
seas/video.py
seas/waveletAnalysis.py
seas/waveletFunctions.py
seas/.pytest_cache/.gitignore
seas/.pytest_cache/CACHEDIR.TAG
seas/.pytest_cache/README.md
seas/.pytest_cache/v/cache/nodeids
seas/.pytest_cache/v/cache/stepwise
seas-0.0.5.dist-info/METADATA
seas-0.0.5.dist-info/WHEEL
seas-0.0.5.dist-info/licenses/LICENSE
seas-0.0.5.dist-info/RECORD
